LICENSE
README.md
setup.py
maya/__main__.py
mayonnaise.egg-info/PKG-INFO
mayonnaise.egg-info/SOURCES.txt
mayonnaise.egg-info/dependency_links.txt
mayonnaise.egg-info/requires.txt
mayonnaise.egg-info/top_level.txt