Metadata-Version: 2.1
Name: mayonnaise
Version: 0.1.0
Summary: Youtube cli interface for downloading media
Home-page: https://github.com/zeionara/maya
Author: Zeio Nara
Author-email: zeionara@gmail.com
Classifier: Programming Language :: Python :: 3.10
License-File: LICENSE
